ASDFGH/__init__.py
ASDFGH/clock.py
asdfgh-0.1.2.dist-info/licenses/LICENSE
tests/__init__.py
tests/test_clock.py
asdfgh-0.1.2.dist-info/METADATA
asdfgh-0.1.2.dist-info/WHEEL
asdfgh-0.1.2.dist-info/entry_points.txt
asdfgh-0.1.2.dist-info/top_level.txt
asdfgh-0.1.2.dist-info/RECORD
