Metadata-Version: 2.4
Name: ASDFGH
Version: 0.1.2
Summary: A terminal clock with retro and plain themes
Keywords: terminal,clock,retro,ascii,time
Requires-Python: >=3.7
License-File: LICENSE
Requires-Dist: colorama>=0.4.0
Dynamic: license-file
